{"add":{"path":"part-00000-cde20f87-df6a-46b2-9a0a-3ecf3a082418-c000.snappy.parquet","partitionValues":{},"size":12237,"modificationTime":1764961095149,"dataChange":true,"stats":"{\"numRecords\":500,\"minValues\":{\"value\":11.27,\"area\":\"Alabama\",\"indicator\":\"Average hourly wage for entry level computer systems analysts in\",\"occupation\":\"Accountants and Auditors\",\"date\":\"2023\"},\"maxValues\":{\"area\":\"Worcester, MA-CT\",\"indicator\":\"Average hourly wage for union production occupations in Detroit.\",\"occupation\":\"Tellers\",\"date\":\"2023\",\"value\":75.7},\"nullCount\":{\"occupation\":0,\"indicator\":0,\"value\":0,\"date\":0,\"area\":0}}","tags":null,"baseRowId":null,"defaultRowCommitVersion":null,"clusteringProvider":null}}
{"commitInfo":{"timestamp":1764961095149,"operation":"WRITE","operationParameters":{"mode":"Append"},"engineInfo":"delta-rs:py-1.2.1","operationMetrics":{"execution_time_ms":1,"num_added_files":1,"num_added_rows":500,"num_partitions":0,"num_removed_files":0},"clientVersion":"delta-rs.py-1.2.1"}}